neon_nodes/__init__.py
neon_nodes/version.py
neon_nodes/voice_client.py
neon_nodes/res/error.wav
neon_nodes/res/start_listening.wav
neon_nodes-0.0.1.dist-info/LICENSE.md
neon_nodes-0.0.1.dist-info/METADATA
neon_nodes-0.0.1.dist-info/WHEEL
neon_nodes-0.0.1.dist-info/top_level.txt
neon_nodes-0.0.1.dist-info/zip-safe
neon_nodes-0.0.1.dist-info/RECORD
