Metadata-Version: 2.1
Name: neon-nodes
Version: 0.0.1
Summary: Neon node clients for Hana
Home-page: https://github.com/NeonGeckoCom/neon-nodes
Author: NeonGecko
Author-email: developers@neon.ai
License: BSD-3-Clause
Classifier: Intended Audience :: Developers
Classifier: Programming Language :: Python :: 3
License-File: LICENSE.md
Provides-Extra: voice-client
Requires-Dist: neon-utils[network] ~=1.9 ; extra == 'voice-client'
Requires-Dist: ovos-dinkum-listener ==0.0.3a29 ; extra == 'voice-client'
Requires-Dist: ovos-vad-plugin-silero ~=0.0.1 ; extra == 'voice-client'
Requires-Dist: ovos-microphone-plugin-alsa ~=0.0.0 ; extra == 'voice-client'
Requires-Dist: ovos-ww-plugin-precise-lite[tflite] ~=0.1 ; extra == 'voice-client'
Requires-Dist: pydub ~=0.25 ; extra == 'voice-client'
Requires-Dist: SpeechRecognition ~=3.10 ; extra == 'voice-client'
Requires-Dist: sdnotify ~=0.3 ; extra == 'voice-client'
Requires-Dist: requests ~=2.28 ; extra == 'voice-client'
Requires-Dist: numpy ~=1.26 ; extra == 'voice-client'
